{
  "namespaces": [
    "public"
  ],
  "name": "public",
  "tables": [
    {
      "columns": {
        "id": {
          "name": "id",
          "type": "uuid",
          "unsigned": false,
          "autoincrement": false,
          "primary": false,
          "nullable": false,
          "mappedType": "uuid"
        },
        "name": {
          "name": "name",
          "type": "varchar(255)",
          "unsigned": false,
          "autoincrement": false,
          "primary": false,
          "nullable": false,
          "mappedType": "string"
        },
        "email": {
          "name": "email",
          "type": "varchar(255)",
          "unsigned": false,
          "autoincrement": false,
          "primary": false,
          "nullable": false,
          "mappedType": "string"
        },
        "password": {
          "name": "password",
          "type": "varchar(255)",
          "unsigned": false,
          "autoincrement": false,
          "primary": false,
          "nullable": false,
          "mappedType": "string"
        }
      },
      "name": "user",
      "schema": "public",
      "indexes": [
        {
          "columnNames": [
            "email"
          ],
          "composite": false,
          "keyName": "user_email_unique",
          "primary": false,
          "unique": true
        },
        {
          "keyName": "user_pkey",
          "columnNames": [
            "id"
          ],
          "composite": false,
          "primary": true,
          "unique": true
        }
      ],
      "checks": [],
      "foreignKeys": {}
    },
    {
      "columns": {
        "id": {
          "name": "id",
          "type": "uuid",
          "unsigned": false,
          "autoincrement": false,
          "primary": false,
          "nullable": false,
          "mappedType": "uuid"
        },
        "name": {
          "name": "name",
          "type": "varchar(255)",
          "unsigned": false,
          "autoincrement": false,
          "primary": false,
          "nullable": true,
          "mappedType": "string"
        },
        "description": {
          "name": "description",
          "type": "varchar(255)",
          "unsigned": false,
          "autoincrement": false,
          "primary": false,
          "nullable": true,
          "mappedType": "string"
        },
        "size": {
          "name": "size",
          "type": "int",
          "unsigned": false,
          "autoincrement": false,
          "primary": false,
          "nullable": true,
          "mappedType": "integer"
        },
        "owner_id": {
          "name": "owner_id",
          "type": "uuid",
          "unsigned": false,
          "autoincrement": false,
          "primary": false,
          "nullable": true,
          "mappedType": "uuid"
        }
      },
      "name": "recipe",
      "schema": "public",
      "indexes": [
        {
          "keyName": "recipe_pkey",
          "columnNames": [
            "id"
          ],
          "composite": false,
          "primary": true,
          "unique": true
        }
      ],
      "checks": [],
      "foreignKeys": {
        "recipe_owner_id_foreign": {
          "constraintName": "recipe_owner_id_foreign",
          "columnNames": [
            "owner_id"
          ],
          "localTableName": "public.recipe",
          "referencedColumnNames": [
            "id"
          ],
          "referencedTableName": "public.user",
          "deleteRule": "set null",
          "updateRule": "cascade"
        }
      }
    },
    {
      "columns": {
        "id": {
          "name": "id",
          "type": "uuid",
          "unsigned": false,
          "autoincrement": false,
          "primary": false,
          "nullable": false,
          "mappedType": "uuid"
        },
        "location": {
          "name": "location",
          "type": "varchar(255)",
          "unsigned": false,
          "autoincrement": false,
          "primary": false,
          "nullable": true,
          "mappedType": "string"
        },
        "capacity": {
          "name": "capacity",
          "type": "int",
          "unsigned": false,
          "autoincrement": false,
          "primary": false,
          "nullable": true,
          "mappedType": "integer"
        }
      },
      "name": "fridge",
      "schema": "public",
      "indexes": [
        {
          "keyName": "fridge_pkey",
          "columnNames": [
            "id"
          ],
          "composite": false,
          "primary": true,
          "unique": true
        }
      ],
      "checks": [],
      "foreignKeys": {}
    },
    {
      "columns": {
        "id": {
          "name": "id",
          "type": "uuid",
          "unsigned": false,
          "autoincrement": false,
          "primary": false,
          "nullable": false,
          "mappedType": "uuid"
        },
        "type": {
          "name": "type",
          "type": "varchar(255)",
          "unsigned": false,
          "autoincrement": false,
          "primary": false,
          "nullable": true,
          "mappedType": "string"
        },
        "name": {
          "name": "name",
          "type": "varchar(255)",
          "unsigned": false,
          "autoincrement": false,
          "primary": false,
          "nullable": true,
          "mappedType": "string"
        },
        "size": {
          "name": "size",
          "type": "int",
          "unsigned": false,
          "autoincrement": false,
          "primary": false,
          "nullable": true,
          "mappedType": "integer"
        },
        "fridge_id": {
          "name": "fridge_id",
          "type": "uuid",
          "unsigned": false,
          "autoincrement": false,
          "primary": false,
          "nullable": true,
          "mappedType": "uuid"
        },
        "owner_id": {
          "name": "owner_id",
          "type": "uuid",
          "unsigned": false,
          "autoincrement": false,
          "primary": false,
          "nullable": true,
          "mappedType": "uuid"
        }
      },
      "name": "product",
      "schema": "public",
      "indexes": [
        {
          "keyName": "product_pkey",
          "columnNames": [
            "id"
          ],
          "composite": false,
          "primary": true,
          "unique": true
        }
      ],
      "checks": [],
      "foreignKeys": {
        "product_fridge_id_foreign": {
          "constraintName": "product_fridge_id_foreign",
          "columnNames": [
            "fridge_id"
          ],
          "localTableName": "public.product",
          "referencedColumnNames": [
            "id"
          ],
          "referencedTableName": "public.fridge",
          "deleteRule": "set null",
          "updateRule": "cascade"
        },
        "product_owner_id_foreign": {
          "constraintName": "product_owner_id_foreign",
          "columnNames": [
            "owner_id"
          ],
          "localTableName": "public.product",
          "referencedColumnNames": [
            "id"
          ],
          "referencedTableName": "public.user",
          "deleteRule": "set null",
          "updateRule": "cascade"
        }
      }
    },
    {
      "columns": {
        "id": {
          "name": "id",
          "type": "uuid",
          "unsigned": false,
          "autoincrement": false,
          "primary": false,
          "nullable": false,
          "mappedType": "uuid"
        },
        "type": {
          "name": "type",
          "type": "int",
          "unsigned": false,
          "autoincrement": false,
          "primary": false,
          "nullable": false,
          "mappedType": "integer"
        },
        "product_id": {
          "name": "product_id",
          "type": "uuid",
          "unsigned": false,
          "autoincrement": false,
          "primary": false,
          "nullable": false,
          "mappedType": "uuid"
        },
        "recipe_id": {
          "name": "recipe_id",
          "type": "uuid",
          "unsigned": false,
          "autoincrement": false,
          "primary": false,
          "nullable": false,
          "mappedType": "uuid"
        }
      },
      "name": "product_recipe",
      "schema": "public",
      "indexes": [
        {
          "keyName": "product_recipe_pkey",
          "columnNames": [
            "id"
          ],
          "composite": false,
          "primary": true,
          "unique": true
        }
      ],
      "checks": [],
      "foreignKeys": {
        "product_recipe_product_id_foreign": {
          "constraintName": "product_recipe_product_id_foreign",
          "columnNames": [
            "product_id"
          ],
          "localTableName": "public.product_recipe",
          "referencedColumnNames": [
            "id"
          ],
          "referencedTableName": "public.product",
          "updateRule": "cascade"
        },
        "product_recipe_recipe_id_foreign": {
          "constraintName": "product_recipe_recipe_id_foreign",
          "columnNames": [
            "recipe_id"
          ],
          "localTableName": "public.product_recipe",
          "referencedColumnNames": [
            "id"
          ],
          "referencedTableName": "public.recipe",
          "updateRule": "cascade"
        }
      }
    }
  ]
}
